{
    "name": "App\\Http\\Controllers\\GuardianController",
    "line": 16,
    "short_desc": "",
    "long_desc": "",
    "hint": null,
    "tags": [],
    "namespace": "App\\Http\\Controllers",
    "file": "\/var\/www\/html\/kitamatch\/app\/Http\/Controllers\/GuardianController.php",
    "relative_file": null,
    "hash": "bf9ed831eaaa7486c860da3ac04373be59a72041",
    "parent": "App\\Http\\Controllers\\Controller",
    "modifiers": 0,
    "is_trait": false,
    "is_interface": false,
    "aliases": {
        "Request": "Illuminate\\Http\\Request",
        "UpdateGuardianRequest": "App\\Http\\Requests\\UpdateGuardianRequest",
        "Requests": "App\\Http\\Requests",
        "Controller": "App\\Http\\Controllers\\Controller",
        "Guardian": "App\\Guardian",
        "Applicant": "App\\Applicant",
        "User": "App\\User",
        "Code": "App\\Code",
        "GuardianVerified": "App\\Mail\\GuardianVerified",
        "Mail": "Illuminate\\Support\\Facades\\Mail"
    },
    "errors": [],
    "interfaces": [],
    "traits": [],
    "properties": [],
    "methods": {
        "store": {
            "name": "store",
            "line": 18,
            "short_desc": "",
            "long_desc": "",
            "hint": null,
            "hint_desc": null,
            "tags": [],
            "modifiers": 1,
            "is_by_ref": "",
            "exceptions": [],
            "errors": [],
            "parameters": {
                "request": {
                    "name": "request",
                    "line": 18,
                    "short_desc": null,
                    "long_desc": null,
                    "hint": [
                        [
                            "\\Illuminate\\Http\\Request",
                            false
                        ]
                    ],
                    "tags": [],
                    "modifiers": {
                        "nodeType": "Name_FullyQualified",
                        "parts": [
                            "Illuminate",
                            "Http",
                            "Request"
                        ],
                        "attributes": {
                            "startLine": 18,
                            "endLine": 18
                        }
                    },
                    "default": null,
                    "variadic": false,
                    "is_by_ref": false
                }
            }
        },
        "show": {
            "name": "show",
            "line": 36,
            "short_desc": "",
            "long_desc": "",
            "hint": null,
            "hint_desc": null,
            "tags": [],
            "modifiers": 1,
            "is_by_ref": "",
            "exceptions": [],
            "errors": [],
            "parameters": {
                "gid": {
                    "name": "gid",
                    "line": 36,
                    "short_desc": null,
                    "long_desc": null,
                    "hint": null,
                    "tags": [],
                    "modifiers": null,
                    "default": null,
                    "variadic": false,
                    "is_by_ref": false
                }
            }
        },
        "edit": {
            "name": "edit",
            "line": 44,
            "short_desc": "",
            "long_desc": "",
            "hint": null,
            "hint_desc": null,
            "tags": [],
            "modifiers": 1,
            "is_by_ref": "",
            "exceptions": [],
            "errors": [],
            "parameters": {
                "request": {
                    "name": "request",
                    "line": 44,
                    "short_desc": null,
                    "long_desc": null,
                    "hint": [
                        [
                            "\\App\\Http\\Requests\\UpdateGuardianRequest",
                            false
                        ]
                    ],
                    "tags": [],
                    "modifiers": {
                        "nodeType": "Name_FullyQualified",
                        "parts": [
                            "App",
                            "Http",
                            "Requests",
                            "UpdateGuardianRequest"
                        ],
                        "attributes": {
                            "startLine": 44,
                            "endLine": 44
                        }
                    },
                    "default": null,
                    "variadic": false,
                    "is_by_ref": false
                },
                "gid": {
                    "name": "gid",
                    "line": 44,
                    "short_desc": null,
                    "long_desc": null,
                    "hint": null,
                    "tags": [],
                    "modifiers": null,
                    "default": null,
                    "variadic": false,
                    "is_by_ref": false
                }
            }
        },
        "update": {
            "name": "update",
            "line": 50,
            "short_desc": "",
            "long_desc": "",
            "hint": null,
            "hint_desc": null,
            "tags": [],
            "modifiers": 1,
            "is_by_ref": "",
            "exceptions": [],
            "errors": [],
            "parameters": {
                "request": {
                    "name": "request",
                    "line": 50,
                    "short_desc": null,
                    "long_desc": null,
                    "hint": [
                        [
                            "\\App\\Http\\Requests\\UpdateGuardianRequest",
                            false
                        ]
                    ],
                    "tags": [],
                    "modifiers": {
                        "nodeType": "Name_FullyQualified",
                        "parts": [
                            "App",
                            "Http",
                            "Requests",
                            "UpdateGuardianRequest"
                        ],
                        "attributes": {
                            "startLine": 50,
                            "endLine": 50
                        }
                    },
                    "default": null,
                    "variadic": false,
                    "is_by_ref": false
                }
            }
        },
        "all": {
            "name": "all",
            "line": 66,
            "short_desc": "",
            "long_desc": "",
            "hint": null,
            "hint_desc": null,
            "tags": [],
            "modifiers": 1,
            "is_by_ref": "",
            "exceptions": [],
            "errors": [],
            "parameters": []
        },
        "verify": {
            "name": "verify",
            "line": 80,
            "short_desc": "",
            "long_desc": "",
            "hint": null,
            "hint_desc": null,
            "tags": [],
            "modifiers": 1,
            "is_by_ref": "",
            "exceptions": [],
            "errors": [],
            "parameters": {
                "gid": {
                    "name": "gid",
                    "line": 80,
                    "short_desc": null,
                    "long_desc": null,
                    "hint": null,
                    "tags": [],
                    "modifiers": null,
                    "default": null,
                    "variadic": false,
                    "is_by_ref": false
                }
            }
        },
        "validator": {
            "name": "validator",
            "line": 98,
            "short_desc": "",
            "long_desc": "",
            "hint": null,
            "hint_desc": null,
            "tags": [],
            "modifiers": 2,
            "is_by_ref": "",
            "exceptions": [],
            "errors": [],
            "parameters": {
                "data": {
                    "name": "data",
                    "line": 98,
                    "short_desc": null,
                    "long_desc": null,
                    "hint": [
                        [
                            "array",
                            false
                        ]
                    ],
                    "tags": [],
                    "modifiers": "array",
                    "default": null,
                    "variadic": false,
                    "is_by_ref": false
                }
            }
        }
    },
    "constants": []
}