{
    "name": "App\\Criterium",
    "line": 8,
    "short_desc": "",
    "long_desc": "",
    "hint": null,
    "tags": [],
    "namespace": "App",
    "file": "\/var\/www\/html\/kitamatch\/app\/Criterium.php",
    "relative_file": null,
    "hash": "d377ab5cdec149553fd9ee78f002ddb126e076bd",
    "parent": "Illuminate\\Database\\Eloquent\\Model",
    "modifiers": 0,
    "is_trait": false,
    "is_interface": false,
    "aliases": {
        "Model": "Illuminate\\Database\\Eloquent\\Model",
        "DB": "Illuminate\\Support\\Facades\\DB"
    },
    "errors": [],
    "interfaces": [],
    "traits": [],
    "properties": {
        "primaryKey": {
            "name": "primaryKey",
            "line": 13,
            "short_desc": "",
            "long_desc": "",
            "hint": null,
            "hint_desc": null,
            "tags": [],
            "modifiers": 1,
            "default": {
                "nodeType": "Scalar_String",
                "value": "cid",
                "attributes": {
                    "startLine": 13,
                    "endLine": 13,
                    "kind": 1
                }
            },
            "errors": []
        },
        "table": {
            "name": "table",
            "line": 14,
            "short_desc": "",
            "long_desc": "",
            "hint": null,
            "hint_desc": null,
            "tags": [],
            "modifiers": 2,
            "default": {
                "nodeType": "Scalar_String",
                "value": "criteria",
                "attributes": {
                    "startLine": 14,
                    "endLine": 14,
                    "kind": 1
                }
            },
            "errors": []
        }
    },
    "methods": [],
    "constants": []
}